quick_context/__init__.py
quick_context/admin.py
quick_context/apps.py
quick_context/context_processors.py
quick_context/models.py
quick_context/tests.py
quick_context/views.py
quick_context/migrations/__init__.py
django_quick_context-1.4.0.dist-info/LICENSE.txt
django_quick_context-1.4.0.dist-info/METADATA
django_quick_context-1.4.0.dist-info/WHEEL
django_quick_context-1.4.0.dist-info/top_level.txt
django_quick_context-1.4.0.dist-info/RECORD
